candig_ingest-1.5.0-py3.6-nspkg.pth
candig/ingest/__init__.py
candig/ingest/_version.py
candig/ingest/ingest.py
candig/ingest/load_tiers.py
candig/ingest/tier/project_tiers.tsv
candig/ingest_logging/__init__.py
candig/ingest_logging/logging.py
candig_ingest-1.5.0.dist-info/LICENSE
candig_ingest-1.5.0.dist-info/METADATA
candig_ingest-1.5.0.dist-info/WHEEL
candig_ingest-1.5.0.dist-info/entry_points.txt
candig_ingest-1.5.0.dist-info/namespace_packages.txt
candig_ingest-1.5.0.dist-info/top_level.txt
candig_ingest-1.5.0.dist-info/RECORD
