Metadata-Version: 2.1
Name: candig-ingest
Version: 1.5.0
Summary: Routines for ingesting metadata to a CanDIG repository
Home-page: https://github.com/CanDIG/candig-ingest.git
Author: CanDIG team
Author-email: candig@bcgsc.ca
License: GNU General Public License v3
Keywords: candig-ingest
Platform: UNKNOWN
Classifier: Natural Language :: English
Classifier: Programming Language :: Python :: 3.6
Classifier: Topic :: Scientific/Engineering :: Bio-Informatics
Requires-Dist: docopt
Requires-Dist: candig-server
Requires-Dist: pandas
